Workbook

Sheet Assumptions
A1: MMM Scoring — Assumptions
A2: 30yr Fixed Rate (%) | B2: 0.0747
A3: Down Payment (%) | B3: 0.25
A4: Expense Ratio (%) | B4: 0.35
A6: Blue cells = inputs you can change. All scores recalculate automatically.

Sheet Scored Listings
A1: Listing Link | B1: Address | C1: Zip | D1: County | E1: Type | F1: Units | G1: Price ($) | H1: Est. Rent ($/mo) | I1: 1% Ratio | J1: NOI ($/mo) | K1: Monthly Mortgage ($/mo) | L1: Net Cash Flow ($/mo) | M1: 1% Score | N1: CF Score | O1: Location Score | P1: Total Score | Q1: MLS ID | R1: STR Flag | S1: Previously Featured?
A2: =HYPERLINK("https://www.google.com/search?q=A11965762+Miami+MLS+listing", "A11965762") | B2: 2425 NW 28th St | C2: 33142 | D2: Miami-Dade County | E2: Triplex | F2: 3 | G2: 614000 | H2: 6900 | I2: =H2/G2 | J2: =H2*(1-Assumptions!$B$4) | K2: =PMT(Assumptions!$B$2/12, 360, -G2*(1-Assumptions!$B$3)) | L2: =J2+K2 | M2: =IF(I2>=0.01,50,IF(I2>=0.0095,37,IF(I2>=0.009,25,12))) | N2: =IF(L2>=2000,30,IF(L2>=1000,20,IF(L2>=500,10,5))) | O2: 20 | P2: =M2+N2+O2 | Q2: A11965762
A3: =HYPERLINK("https://www.google.com/search?q=A11960470+Miami+MLS+listing", "A11960470") | B3: 6241 NW Miami Pl | C3: 33150 | D3: Miami-Dade County | E3: Duplex | F3: 2 | G3: 899000 | H3: 9800 | I3: =H3/G3 | J3: =H3*(1-Assumptions!$B$4) | K3: =PMT(Assumptions!$B$2/12, 360, -G3*(1-Assumptions!$B$3)) | L3: =J3+K3 | M3: =IF(I3>=0.01,50,IF(I3>=0.0095,37,IF(I3>=0.009,25,12))) | N3: =IF(L3>=2000,30,IF(L3>=1000,20,IF(L3>=500,10,5))) | O3: 20 | P3: =M3+N3+O3 | Q3: A11960470
A4: =HYPERLINK("https://www.google.com/search?q=A11969029+Miami+MLS+listing", "A11969029") | B4: 356 SW 2nd Pl | C4: 33060 | D4: Broward County | E4: Fourplex | F4: 4 | G4: 750000 | H4: 7650 | I4: =H4/G4 | J4: =H4*(1-Assumptions!$B$4) | K4: =PMT(Assumptions!$B$2/12, 360, -G4*(1-Assumptions!$B$3)) | L4: =J4+K4 | M4: =IF(I4>=0.01,50,IF(I4>=0.0095,37,IF(I4>=0.009,25,12))) | N4: =IF(L4>=2000,30,IF(L4>=1000,20,IF(L4>=500,10,5))) | O4: 13 | P4: =M4+N4+O4 | Q4: A11969029
A5: =HYPERLINK("https://www.google.com/search?q=A11919736+Miami+MLS+listing", "A11919736") | B5: 2601 N 66th Ave | C5: 33024 | D5: Broward County | E5: Fourplex | F5: 4 | G5: 615000 | H5: 7500 | I5: =H5/G5 | J5: =H5*(1-Assumptions!$B$4) | K5: =PMT(Assumptions!$B$2/12, 360, -G5*(1-Assumptions!$B$3)) | L5: =J5+K5 | M5: =IF(I5>=0.01,50,IF(I5>=0.0095,37,IF(I5>=0.009,25,12))) | N5: =IF(L5>=2000,30,IF(L5>=1000,20,IF(L5>=500,10,5))) | O5: 13 | P5: =M5+N5+O5 | Q5: A11919736
A6: =HYPERLINK("https://www.google.com/search?q=A11744047+Miami+MLS+listing", "A11744047") | B6: 655 NE 135th St | C6: 33161 | D6: Miami-Dade County | E6: Duplex | F6: 2 | G6: 660000 | H6: 6700 | I6: =H6/G6 | J6: =H6*(1-Assumptions!$B$4) | K6: =PMT(Assumptions!$B$2/12, 360, -G6*(1-Assumptions!$B$3)) | L6: =J6+K6 | M6: =IF(I6>=0.01,50,IF(I6>=0.0095,37,IF(I6>=0.009,25,12))) | N6: =IF(L6>=2000,30,IF(L6>=1000,20,IF(L6>=500,10,5))) | O6: 20 | P6: =M6+N6+O6 | Q6: A11744047
A7: =HYPERLINK("https://www.google.com/search?q=A11922821+Miami+MLS+listing", "A11922821") | B7: 2912 NW 32nd St | C7: 33142 | D7: Miami-Dade County | E7: Duplex | F7: 2 | G7: 500000 | H7: 5000 | I7: =H7/G7 | J7: =H7*(1-Assumptions!$B$4) | K7: =PMT(Assumptions!$B$2/12, 360, -G7*(1-Assumptions!$B$3)) | L7: =J7+K7 | M7: =IF(I7>=0.01,50,IF(I7>=0.0095,37,IF(I7>=0.009,25,12))) | N7: =IF(L7>=2000,30,IF(L7>=1000,20,IF(L7>=500,10,5))) | O7: 20 | P7: =M7+N7+O7 | Q7: A11922821
A8: =HYPERLINK("https://www.google.com/search?q=A11901546+Miami+MLS+listing", "A11901546") | B8: 2930 NW 14th Ave | C8: 33142 | D8: Miami-Dade County | E8: Fourplex | F8: 4 | G8: 689500 | H8: 6940 | I8: =H8/G8 | J8: =H8*(1-Assumptions!$B$4) | K8: =PMT(Assumptions!$B$2/12, 360, -G8*(1-Assumptions!$B$3)) | L8: =J8+K8 | M8: =IF(I8>=0.01,50,IF(I8>=0.0095,37,IF(I8>=0.009,25,12))) | N8: =IF(L8>=2000,30,IF(L8>=1000,20,IF(L8>=500,10,5))) | O8: 20 | P8: =M8+N8+O8 | Q8: A11901546
A9: =HYPERLINK("https://www.google.com/search?q=A11839261+Miami+MLS+listing", "A11839261") | B9: 2240 Simms St | C9: 33020 | D9: Broward County | E9: Fourplex | F9: 4 | G9: 845000 | H9: 8396 | I9: =H9/G9 | J9: =H9*(1-Assumptions!$B$4) | K9: =PMT(Assumptions!$B$2/12, 360, -G9*(1-Assumptions!$B$3)) | L9: =J9+K9 | M9: =IF(I9>=0.01,50,IF(I9>=0.0095,37,IF(I9>=0.009,25,12))) | N9: =IF(L9>=2000,30,IF(L9>=1000,20,IF(L9>=500,10,5))) | O9: 13 | P9: =M9+N9+O9 | Q9: A11839261
A10: =HYPERLINK("https://www.google.com/search?q=A11967277+Miami+MLS+listing", "A11967277") | B10: 4381 Purdy Ln | C10: 33406 | D10: Palm Beach County | E10: Triplex | F10: 3 | G10: 750000 | H10: 7250 | I10: =H10/G10 | J10: =H10*(1-Assumptions!$B$4) | K10: =PMT(Assumptions!$B$2/12, 360, -G10*(1-Assumptions!$B$3)) | L10: =J10+K10 | M10: =IF(I10>=0.01,50,IF(I10>=0.0095,37,IF(I10>=0.009,25,12))) | N10: =IF(L10>=2000,30,IF(L10>=1000,20,IF(L10>=500,10,5))) | O10: 13 | P10: =M10+N10+O10 | Q10: A11967277
A11: =HYPERLINK("https://www.google.com/search?q=A11969394+Miami+MLS+listing", "A11969394") | B11: 208 SW 1st Ct | C11: 33060 | D11: Broward County | E11: Triplex | F11: 3 | G11: 700000 | H11: 6800 | I11: =H11/G11 | J11: =H11*(1-Assumptions!$B$4) | K11: =PMT(Assumptions!$B$2/12, 360, -G11*(1-Assumptions!$B$3)) | L11: =J11+K11 | M11: =IF(I11>=0.01,50,IF(I11>=0.0095,37,IF(I11>=0.009,25,12))) | N11: =IF(L11>=2000,30,IF(L11>=1000,20,IF(L11>=500,10,5))) | O11: 13 | P11: =M11+N11+O11 | Q11: A11969394
A12: =HYPERLINK("https://www.google.com/search?q=A11893787+Miami+MLS+listing", "A11893787") | B12: 1102 NW 103rd Street | C12: 33150 | D12: Miami-Dade County | E12: Triplex | F12: 3 | G12: 749000 | H12: 6975 | I12: =H12/G12 | J12: =H12*(1-Assumptions!$B$4) | K12: =PMT(Assumptions!$B$2/12, 360, -G12*(1-Assumptions!$B$3)) | L12: =J12+K12 | M12: =IF(I12>=0.01,50,IF(I12>=0.0095,37,IF(I12>=0.009,25,12))) | N12: =IF(L12>=2000,30,IF(L12>=1000,20,IF(L12>=500,10,5))) | O12: 20 | P12: =M12+N12+O12 | Q12: A11893787
A13: =HYPERLINK("https://www.google.com/search?q=A11893641+Miami+MLS+listing", "A11893641") | B13: 10290 SW 174th Ter | C13: 33157 | D13: Miami-Dade County | E13: Duplex | F13: 2 | G13: 699900 | H13: 6400 | I13: =H13/G13 | J13: =H13*(1-Assumptions!$B$4) | K13: =PMT(Assumptions!$B$2/12, 360, -G13*(1-Assumptions!$B$3)) | L13: =J13+K13 | M13: =IF(I13>=0.01,50,IF(I13>=0.0095,37,IF(I13>=0.009,25,12))) | N13: =IF(L13>=2000,30,IF(L13>=1000,20,IF(L13>=500,10,5))) | O13: 16 | P13: =M13+N13+O13 | Q13: A11893641
A14: =HYPERLINK("https://www.google.com/search?q=A11889559+Miami+MLS+listing", "A11889559") | B14: 276 E 12th St | C14: 33010 | D14: Miami-Dade County | E14: Triplex | F14: 3 | G14: 820000 | H14: 7400 | I14: =H14/G14 | J14: =H14*(1-Assumptions!$B$4) | K14: =PMT(Assumptions!$B$2/12, 360, -G14*(1-Assumptions!$B$3)) | L14: =J14+K14 | M14: =IF(I14>=0.01,50,IF(I14>=0.0095,37,IF(I14>=0.009,25,12))) | N14: =IF(L14>=2000,30,IF(L14>=1000,20,IF(L14>=500,10,5))) | O14: 16 | P14: =M14+N14+O14 | Q14: A11889559
A15: =HYPERLINK("https://www.google.com/search?q=A11977765+Miami+MLS+listing", "A11977765") | B15: 3021 NE 7th Ave | C15: 33064 | D15: Broward County | E15: Fourplex | F15: 4 | G15: 899000 | H15: 8200 | I15: =H15/G15 | J15: =H15*(1-Assumptions!$B$4) | K15: =PMT(Assumptions!$B$2/12, 360, -G15*(1-Assumptions!$B$3)) | L15: =J15+K15 | M15: =IF(I15>=0.01,50,IF(I15>=0.0095,37,IF(I15>=0.009,25,12))) | N15: =IF(L15>=2000,30,IF(L15>=1000,20,IF(L15>=500,10,5))) | O15: 13 | P15: =M15+N15+O15 | Q15: A11977765
A16: =HYPERLINK("https://www.google.com/search?q=A11943542+Miami+MLS+listing", "A11943542") | B16: 3270 SW 7th St | C16: 33135 | D16: Miami-Dade County | E16: Duplex | F16: 2 | G16: 1125000 | H16: 6400 | I16: =H16/G16 | J16: =H16*(1-Assumptions!$B$4) | K16: =PMT(Assumptions!$B$2/12, 360, -G16*(1-Assumptions!$B$3)) | L16: =J16+K16 | M16: =IF(I16>=0.01,50,IF(I16>=0.0095,37,IF(I16>=0.009,25,12))) | N16: =IF(L16>=2000,30,IF(L16>=1000,20,IF(L16>=500,10,5))) | O16: 20 | P16: =M16+N16+O16 | Q16: A11943542
A17: =HYPERLINK("https://www.google.com/search?q=A11923026+Miami+MLS+listing", "A11923026") | B17: 2416 NW 79th Ter | C17: 33147 | D17: Miami-Dade County | E17: Triplex | F17: 3 | G17: 759000 | H17: 6482 | I17: =H17/G17 | J17: =H17*(1-Assumptions!$B$4) | K17: =PMT(Assumptions!$B$2/12, 360, -G17*(1-Assumptions!$B$3)) | L17: =J17+K17 | M17: =IF(I17>=0.01,50,IF(I17>=0.0095,37,IF(I17>=0.009,25,12))) | N17: =IF(L17>=2000,30,IF(L17>=1000,20,IF(L17>=500,10,5))) | O17: 20 | P17: =M17+N17+O17 | Q17: A11923026
A18: =HYPERLINK("https://www.google.com/search?q=A11952604+Miami+MLS+listing", "A11952604") | B18: 3330 NW 4th St | C18: 33125 | D18: Miami-Dade County | E18: Duplex | F18: 2 | G18: 795000 | H18: 5200 | I18: =H18/G18 | J18: =H18*(1-Assumptions!$B$4) | K18: =PMT(Assumptions!$B$2/12, 360, -G18*(1-Assumptions!$B$3)) | L18: =J18+K18 | M18: =IF(I18>=0.01,50,IF(I18>=0.0095,37,IF(I18>=0.009,25,12))) | N18: =IF(L18>=2000,30,IF(L18>=1000,20,IF(L18>=500,10,5))) | O18: 20 | P18: =M18+N18+O18 | Q18: A11952604
A19: =HYPERLINK("https://www.google.com/search?q=A11868974+Miami+MLS+listing", "A11868974") | B19: 1255 NE 110th Ter | C19: 33161 | D19: Miami-Dade County | E19: Duplex | F19: 2 | G19: 660000 | H19: 5100 | I19: =H19/G19 | J19: =H19*(1-Assumptions!$B$4) | K19: =PMT(Assumptions!$B$2/12, 360, -G19*(1-Assumptions!$B$3)) | L19: =J19+K19 | M19: =IF(I19>=0.01,50,IF(I19>=0.0095,37,IF(I19>=0.009,25,12))) | N19: =IF(L19>=2000,30,IF(L19>=1000,20,IF(L19>=500,10,5))) | O19: 20 | P19: =M19+N19+O19 | Q19: A11868974
A20: =HYPERLINK("https://www.google.com/search?q=A11911368+Miami+MLS+listing", "A11911368") | B20: 1247 NW 28th St | C20: 33142 | D20: Miami-Dade County | E20: Duplex | F20: 2 | G20: 825000 | H20: 6400 | I20: =H20/G20 | J20: =H20*(1-Assumptions!$B$4) | K20: =PMT(Assumptions!$B$2/12, 360, -G20*(1-Assumptions!$B$3)) | L20: =J20+K20 | M20: =IF(I20>=0.01,50,IF(I20>=0.0095,37,IF(I20>=0.009,25,12))) | N20: =IF(L20>=2000,30,IF(L20>=1000,20,IF(L20>=500,10,5))) | O20: 20 | P20: =M20+N20+O20 | Q20: A11911368
A21: =HYPERLINK("https://www.google.com/search?q=A11854508+Miami+MLS+listing", "A11854508") | B21: 1701 SW 21st St | C21: 33145 | D21: Miami-Dade County | E21: Duplex | F21: 2 | G21: 899000 | H21: 5100 | I21: =H21/G21 | J21: =H21*(1-Assumptions!$B$4) | K21: =PMT(Assumptions!$B$2/12, 360, -G21*(1-Assumptions!$B$3)) | L21: =J21+K21 | M21: =IF(I21>=0.01,50,IF(I21>=0.0095,37,IF(I21>=0.009,25,12))) | N21: =IF(L21>=2000,30,IF(L21>=1000,20,IF(L21>=500,10,5))) | O21: 20 | P21: =M21+N21+O21 | Q21: A11854508
A22: =HYPERLINK("https://www.google.com/search?q=A11957385+Miami+MLS+listing", "A11957385") | B22: 1362 SW 2nd St | C22: 33135 | D22: Miami-Dade County | E22: Fourplex | F22: 4 | G22: 3990000 | H22: 5100 | I22: =H22/G22 | J22: =H22*(1-Assumptions!$B$4) | K22: =PMT(Assumptions!$B$2/12, 360, -G22*(1-Assumptions!$B$3)) | L22: =J22+K22 | M22: =IF(I22>=0.01,50,IF(I22>=0.0095,37,IF(I22>=0.009,25,12))) | N22: =IF(L22>=2000,30,IF(L22>=1000,20,IF(L22>=500,10,5))) | O22: 20 | P22: =M22+N22+O22 | Q22: A11957385
A23: =HYPERLINK("https://www.google.com/search?q=A11389399+Miami+MLS+listing", "A11389399") | B23: 2855 NW 22nd Ave | C23: 33142 | D23: Miami-Dade County | E23: Fourplex | F23: 4 | G23: 910000 | H23: 6425 | I23: =H23/G23 | J23: =H23*(1-Assumptions!$B$4) | K23: =PMT(Assumptions!$B$2/12, 360, -G23*(1-Assumptions!$B$3)) | L23: =J23+K23 | M23: =IF(I23>=0.01,50,IF(I23>=0.0095,37,IF(I23>=0.009,25,12))) | N23: =IF(L23>=2000,30,IF(L23>=1000,20,IF(L23>=500,10,5))) | O23: 20 | P23: =M23+N23+O23 | Q23: A11389399
A24: =HYPERLINK("https://www.google.com/search?q=A11965310+Miami+MLS+listing", "A11965310") | B24: 1220-1222 NE 110th Ter | C24: 33161 | D24: Miami-Dade County | E24: Triplex | F24: 3 | G24: 749000 | H24: 5095 | I24: =H24/G24 | J24: =H24*(1-Assumptions!$B$4) | K24: =PMT(Assumptions!$B$2/12, 360, -G24*(1-Assumptions!$B$3)) | L24: =J24+K24 | M24: =IF(I24>=0.01,50,IF(I24>=0.0095,37,IF(I24>=0.009,25,12))) | N24: =IF(L24>=2000,30,IF(L24>=1000,20,IF(L24>=500,10,5))) | O24: 20 | P24: =M24+N24+O24 | Q24: A11965310
A25: =HYPERLINK("https://www.google.com/search?q=A11962645+Miami+MLS+listing", "A11962645") | B25: 2900 SW 4th St | C25: 33135 | D25: Miami-Dade County | E25: Duplex | F25: 2 | G25: 975000 | H25: 5050 | I25: =H25/G25 | J25: =H25*(1-Assumptions!$B$4) | K25: =PMT(Assumptions!$B$2/12, 360, -G25*(1-Assumptions!$B$3)) | L25: =J25+K25 | M25: =IF(I25>=0.01,50,IF(I25>=0.0095,37,IF(I25>=0.009,25,12))) | N25: =IF(L25>=2000,30,IF(L25>=1000,20,IF(L25>=500,10,5))) | O25: 20 | P25: =M25+N25+O25 | Q25: A11962645
A26: =HYPERLINK("https://www.google.com/search?q=A11818575+Miami+MLS+listing", "A11818575") | B26: 77 Northwest Blvd | C26: 33126 | D26: Miami-Dade County | E26: Triplex | F26: 3 | G26: 1025000 | H26: 5050 | I26: =H26/G26 | J26: =H26*(1-Assumptions!$B$4) | K26: =PMT(Assumptions!$B$2/12, 360, -G26*(1-Assumptions!$B$3)) | L26: =J26+K26 | M26: =IF(I26>=0.01,50,IF(I26>=0.0095,37,IF(I26>=0.009,25,12))) | N26: =IF(L26>=2000,30,IF(L26>=1000,20,IF(L26>=500,10,5))) | O26: 20 | P26: =M26+N26+O26 | Q26: A11818575
A27: =HYPERLINK("https://www.google.com/search?q=A11913807+Miami+MLS+listing", "A11913807") | B27: 2800 NW 48th St | C27: 33142 | D27: Miami-Dade County | E27: Duplex | F27: 2 | G27: 749900 | H27: 5048 | I27: =H27/G27 | J27: =H27*(1-Assumptions!$B$4) | K27: =PMT(Assumptions!$B$2/12, 360, -G27*(1-Assumptions!$B$3)) | L27: =J27+K27 | M27: =IF(I27>=0.01,50,IF(I27>=0.0095,37,IF(I27>=0.009,25,12))) | N27: =IF(L27>=2000,30,IF(L27>=1000,20,IF(L27>=500,10,5))) | O27: 20 | P27: =M27+N27+O27 | Q27: A11913807
A28: =HYPERLINK("https://www.google.com/search?q=A11950698+Miami+MLS+listing", "A11950698") | B28: 2930 SW 11th ST | C28: 33135 | D28: Miami-Dade County | E28: Duplex | F28: 2 | G28: 965000 | H28: 5000 | I28: =H28/G28 | J28: =H28*(1-Assumptions!$B$4) | K28: =PMT(Assumptions!$B$2/12, 360, -G28*(1-Assumptions!$B$3)) | L28: =J28+K28 | M28: =IF(I28>=0.01,50,IF(I28>=0.0095,37,IF(I28>=0.009,25,12))) | N28: =IF(L28>=2000,30,IF(L28>=1000,20,IF(L28>=500,10,5))) | O28: 20 | P28: =M28+N28+O28 | Q28: A11950698
A29: =HYPERLINK("https://www.google.com/search?q=A11898915+Miami+MLS+listing", "A11898915") | B29: 1230 NE 148th St | C29: 33161 | D29: Miami-Dade County | E29: Duplex | F29: 2 | G29: 695000 | H29: 5000 | I29: =H29/G29 | J29: =H29*(1-Assumptions!$B$4) | K29: =PMT(Assumptions!$B$2/12, 360, -G29*(1-Assumptions!$B$3)) | L29: =J29+K29 | M29: =IF(I29>=0.01,50,IF(I29>=0.0095,37,IF(I29>=0.009,25,12))) | N29: =IF(L29>=2000,30,IF(L29>=1000,20,IF(L29>=500,10,5))) | O29: 20 | P29: =M29+N29+O29 | Q29: A11898915
A30: =HYPERLINK("https://www.google.com/search?q=A11857462+Miami+MLS+listing", "A11857462") | B30: 2367 SW 19th St | C30: 33145 | D30: Miami-Dade County | E30: Duplex | F30: 2 | G30: 1500000 | H30: 5000 | I30: =H30/G30 | J30: =H30*(1-Assumptions!$B$4) | K30: =PMT(Assumptions!$B$2/12, 360, -G30*(1-Assumptions!$B$3)) | L30: =J30+K30 | M30: =IF(I30>=0.01,50,IF(I30>=0.0095,37,IF(I30>=0.009,25,12))) | N30: =IF(L30>=2000,30,IF(L30>=1000,20,IF(L30>=500,10,5))) | O30: 20 | P30: =M30+N30+O30 | Q30: A11857462
A31: =HYPERLINK("https://www.google.com/search?q=A11873597+Miami+MLS+listing", "A11873597") | B31: 272 NW 59th Street | C31: 33127 | D31: Miami-Dade County | E31: Duplex | F31: 2 | G31: 1400000 | H31: 6500 | I31: =H31/G31 | J31: =H31*(1-Assumptions!$B$4) | K31: =PMT(Assumptions!$B$2/12, 360, -G31*(1-Assumptions!$B$3)) | L31: =J31+K31 | M31: =IF(I31>=0.01,50,IF(I31>=0.0095,37,IF(I31>=0.009,25,12))) | N31: =IF(L31>=2000,30,IF(L31>=1000,20,IF(L31>=500,10,5))) | O31: 20 | P31: =M31+N31+O31 | Q31: A11873597
A32: =HYPERLINK("https://www.google.com/search?q=A11870712+Miami+MLS+listing", "A11870712") | B32: 1450 NW 35th St | C32: 33142 | D32: Miami-Dade County | E32: Duplex | F32: 2 | G32: 679900 | H32: 5295 | I32: =H32/G32 | J32: =H32*(1-Assumptions!$B$4) | K32: =PMT(Assumptions!$B$2/12, 360, -G32*(1-Assumptions!$B$3)) | L32: =J32+K32 | M32: =IF(I32>=0.01,50,IF(I32>=0.0095,37,IF(I32>=0.009,25,12))) | N32: =IF(L32>=2000,30,IF(L32>=1000,20,IF(L32>=500,10,5))) | O32: 20 | P32: =M32+N32+O32 | Q32: A11870712
A33: =HYPERLINK("https://www.google.com/search?q=A11937235+Miami+MLS+listing", "A11937235") | B33: 890 NW 55th St | C33: 33127 | D33: Miami-Dade County | E33: Duplex | F33: 2 | G33: 795000 | H33: 5000 | I33: =H33/G33 | J33: =H33*(1-Assumptions!$B$4) | K33: =PMT(Assumptions!$B$2/12, 360, -G33*(1-Assumptions!$B$3)) | L33: =J33+K33 | M33: =IF(I33>=0.01,50,IF(I33>=0.0095,37,IF(I33>=0.009,25,12))) | N33: =IF(L33>=2000,30,IF(L33>=1000,20,IF(L33>=500,10,5))) | O33: 20 | P33: =M33+N33+O33 | Q33: A11937235
A34: =HYPERLINK("https://www.google.com/search?q=A11974034+Miami+MLS+listing", "A11974034") | B34: 7001 NW 6th Ave | C34: 33150 | D34: Miami-Dade County | E34: Duplex | F34: 2 | G34: 599000 | H34: 5000 | I34: =H34/G34 | J34: =H34*(1-Assumptions!$B$4) | K34: =PMT(Assumptions!$B$2/12, 360, -G34*(1-Assumptions!$B$3)) | L34: =J34+K34 | M34: =IF(I34>=0.01,50,IF(I34>=0.0095,37,IF(I34>=0.009,25,12))) | N34: =IF(L34>=2000,30,IF(L34>=1000,20,IF(L34>=500,10,5))) | O34: 20 | P34: =M34+N34+O34 | Q34: A11974034
A35: =HYPERLINK("https://www.google.com/search?q=A11908596+Miami+MLS+listing", "A11908596") | B35: 5511 NW 5th Ct | C35: 33127 | D35: Miami-Dade County | E35: Duplex | F35: 2 | G35: 749000 | H35: 4950 | I35: =H35/G35 | J35: =H35*(1-Assumptions!$B$4) | K35: =PMT(Assumptions!$B$2/12, 360, -G35*(1-Assumptions!$B$3)) | L35: =J35+K35 | M35: =IF(I35>=0.01,50,IF(I35>=0.0095,37,IF(I35>=0.009,25,12))) | N35: =IF(L35>=2000,30,IF(L35>=1000,20,IF(L35>=500,10,5))) | O35: 20 | P35: =M35+N35+O35 | Q35: A11908596
A36: =HYPERLINK("https://www.google.com/search?q=A11962171+Miami+MLS+listing", "A11962171") | B36: 201 S Biscayne River Dr #0 | C36: 33169 | D36: Miami-Dade County | E36: Duplex | F36: 2 | G36: 980000 | H36: 4950 | I36: =H36/G36 | J36: =H36*(1-Assumptions!$B$4) | K36: =PMT(Assumptions!$B$2/12, 360, -G36*(1-Assumptions!$B$3)) | L36: =J36+K36 | M36: =IF(I36>=0.01,50,IF(I36>=0.0095,37,IF(I36>=0.009,25,12))) | N36: =IF(L36>=2000,30,IF(L36>=1000,20,IF(L36>=500,10,5))) | O36: 20 | P36: =M36+N36+O36 | Q36: A11962171
A37: =HYPERLINK("https://www.google.com/search?q=A11612506+Miami+MLS+listing", "A11612506") | B37: 3100 NW 92nd St | C37: 33147 | D37: Miami-Dade County | E37: Duplex | F37: 2 | G37: 564000 | H37: 4900 | I37: =H37/G37 | J37: =H37*(1-Assumptions!$B$4) | K37: =PMT(Assumptions!$B$2/12, 360, -G37*(1-Assumptions!$B$3)) | L37: =J37+K37 | M37: =IF(I37>=0.01,50,IF(I37>=0.0095,37,IF(I37>=0.009,25,12))) | N37: =IF(L37>=2000,30,IF(L37>=1000,20,IF(L37>=500,10,5))) | O37: 20 | P37: =M37+N37+O37 | Q37: A11612506
A38: =HYPERLINK("https://www.google.com/search?q=A11819098+Miami+MLS+listing", "A11819098") | B38: 829 SW 19th Ave | C38: 33135 | D38: Miami-Dade County | E38: Fourplex | F38: 4 | G38: 2200000 | H38: 4900 | I38: =H38/G38 | J38: =H38*(1-Assumptions!$B$4) | K38: =PMT(Assumptions!$B$2/12, 360, -G38*(1-Assumptions!$B$3)) | L38: =J38+K38 | M38: =IF(I38>=0.01,50,IF(I38>=0.0095,37,IF(I38>=0.009,25,12))) | N38: =IF(L38>=2000,30,IF(L38>=1000,20,IF(L38>=500,10,5))) | O38: 20 | P38: =M38+N38+O38 | Q38: A11819098
A39: =HYPERLINK("https://www.google.com/search?q=A11964838+Miami+MLS+listing", "A11964838") | B39: 36 NW 151st St | C39: 33169 | D39: Miami-Dade County | E39: Duplex | F39: 2 | G39: 725000 | H39: 4850 | I39: =H39/G39 | J39: =H39*(1-Assumptions!$B$4) | K39: =PMT(Assumptions!$B$2/12, 360, -G39*(1-Assumptions!$B$3)) | L39: =J39+K39 | M39: =IF(I39>=0.01,50,IF(I39>=0.0095,37,IF(I39>=0.009,25,12))) | N39: =IF(L39>=2000,30,IF(L39>=1000,20,IF(L39>=500,10,5))) | O39: 20 | P39: =M39+N39+O39 | Q39: A11964838
A40: =HYPERLINK("https://www.google.com/search?q=A11811435+Miami+MLS+listing", "A11811435") | B40: 1237 NW 33rd Ave | C40: 33125 | D40: Miami-Dade County | E40: Duplex | F40: 2 | G40: 850000 | H40: 4800 | I40: =H40/G40 | J40: =H40*(1-Assumptions!$B$4) | K40: =PMT(Assumptions!$B$2/12, 360, -G40*(1-Assumptions!$B$3)) | L40: =J40+K40 | M40: =IF(I40>=0.01,50,IF(I40>=0.0095,37,IF(I40>=0.009,25,12))) | N40: =IF(L40>=2000,30,IF(L40>=1000,20,IF(L40>=500,10,5))) | O40: 20 | P40: =M40+N40+O40 | Q40: A11811435
A41: =HYPERLINK("https://www.google.com/search?q=A11787663+Miami+MLS+listing", "A11787663") | B41: 1864 NW 88th Ter | C41: 33147 | D41: Miami-Dade County | E41: Duplex | F41: 2 | G41: 615000 | H41: 4800 | I41: =H41/G41 | J41: =H41*(1-Assumptions!$B$4) | K41: =PMT(Assumptions!$B$2/12, 360, -G41*(1-Assumptions!$B$3)) | L41: =J41+K41 | M41: =IF(I41>=0.01,50,IF(I41>=0.0095,37,IF(I41>=0.009,25,12))) | N41: =IF(L41>=2000,30,IF(L41>=1000,20,IF(L41>=500,10,5))) | O41: 20 | P41: =M41+N41+O41 | Q41: A11787663
A42: =HYPERLINK("https://www.google.com/search?q=A11947653+Miami+MLS+listing", "A11947653") | B42: 7546 NW 2nd Ter | C42: 33126 | D42: Miami-Dade County | E42: Duplex | F42: 2 | G42: 799000 | H42: 4650 | I42: =H42/G42 | J42: =H42*(1-Assumptions!$B$4) | K42: =PMT(Assumptions!$B$2/12, 360, -G42*(1-Assumptions!$B$3)) | L42: =J42+K42 | M42: =IF(I42>=0.01,50,IF(I42>=0.0095,37,IF(I42>=0.009,25,12))) | N42: =IF(L42>=2000,30,IF(L42>=1000,20,IF(L42>=500,10,5))) | O42: 20 | P42: =M42+N42+O42 | Q42: A11947653
A43: =HYPERLINK("https://www.google.com/search?q=A11940926+Miami+MLS+listing", "A11940926") | B43: 632 15th St | C43: 33139 | D43: Miami-Dade County | E43: Fourplex | F43: 4 | G43: 3000000 | H43: 4600 | I43: =H43/G43 | J43: =H43*(1-Assumptions!$B$4) | K43: =PMT(Assumptions!$B$2/12, 360, -G43*(1-Assumptions!$B$3)) | L43: =J43+K43 | M43: =IF(I43>=0.01,50,IF(I43>=0.0095,37,IF(I43>=0.009,25,12))) | N43: =IF(L43>=2000,30,IF(L43>=1000,20,IF(L43>=500,10,5))) | O43: 20 | P43: =M43+N43+O43 | Q43: A11940926
A44: =HYPERLINK("https://www.google.com/search?q=A11849114+Miami+MLS+listing", "A11849114") | B44: 1499 NW 32nd St | C44: 33142 | D44: Miami-Dade County | E44: Duplex | F44: 2 | G44: 1100000 | H44: 6500 | I44: =H44/G44 | J44: =H44*(1-Assumptions!$B$4) | K44: =PMT(Assumptions!$B$2/12, 360, -G44*(1-Assumptions!$B$3)) | L44: =J44+K44 | M44: =IF(I44>=0.01,50,IF(I44>=0.0095,37,IF(I44>=0.009,25,12))) | N44: =IF(L44>=2000,30,IF(L44>=1000,20,IF(L44>=500,10,5))) | O44: 20 | P44: =M44+N44+O44 | Q44: A11849114
A45: =HYPERLINK("https://www.google.com/search?q=A11927253+Miami+MLS+listing", "A11927253") | B45: 364 SW 11th St | C45: 33130 | D45: Miami-Dade County | E45: Fourplex | F45: 4 | G45: 3800000 | H45: 6700 | I45: =H45/G45 | J45: =H45*(1-Assumptions!$B$4) | K45: =PMT(Assumptions!$B$2/12, 360, -G45*(1-Assumptions!$B$3)) | L45: =J45+K45 | M45: =IF(I45>=0.01,50,IF(I45>=0.0095,37,IF(I45>=0.009,25,12))) | N45: =IF(L45>=2000,30,IF(L45>=1000,20,IF(L45>=500,10,5))) | O45: 20 | P45: =M45+N45+O45 | Q45: A11927253
A46: =HYPERLINK("https://www.google.com/search?q=A11972427+Miami+MLS+listing", "A11972427") | B46: 1490/1492 NW 38th St | C46: 33142 | D46: Miami-Dade County | E46: Duplex | F46: 2 | G46: 650000 | H46: 5200 | I46: =H46/G46 | J46: =H46*(1-Assumptions!$B$4) | K46: =PMT(Assumptions!$B$2/12, 360, -G46*(1-Assumptions!$B$3)) | L46: =J46+K46 | M46: =IF(I46>=0.01,50,IF(I46>=0.0095,37,IF(I46>=0.009,25,12))) | N46: =IF(L46>=2000,30,IF(L46>=1000,20,IF(L46>=500,10,5))) | O46: 20 | P46: =M46+N46+O46 | Q46: A11972427
A47: =HYPERLINK("https://www.google.com/search?q=A11879356+Miami+MLS+listing", "A11879356") | B47: 2915 SW 4th St | C47: 33135 | D47: Miami-Dade County | E47: Duplex | F47: 2 | G47: 915000 | H47: 5300 | I47: =H47/G47 | J47: =H47*(1-Assumptions!$B$4) | K47: =PMT(Assumptions!$B$2/12, 360, -G47*(1-Assumptions!$B$3)) | L47: =J47+K47 | M47: =IF(I47>=0.01,50,IF(I47>=0.0095,37,IF(I47>=0.009,25,12))) | N47: =IF(L47>=2000,30,IF(L47>=1000,20,IF(L47>=500,10,5))) | O47: 20 | P47: =M47+N47+O47 | Q47: A11879356
A48: =HYPERLINK("https://www.google.com/search?q=A11843123+Miami+MLS+listing", "A11843123") | B48: 2835 SW 37th Ct | C48: 33145 | D48: Miami-Dade County | E48: Triplex | F48: 3 | G48: 845000 | H48: 6350 | I48: =H48/G48 | J48: =H48*(1-Assumptions!$B$4) | K48: =PMT(Assumptions!$B$2/12, 360, -G48*(1-Assumptions!$B$3)) | L48: =J48+K48 | M48: =IF(I48>=0.01,50,IF(I48>=0.0095,37,IF(I48>=0.009,25,12))) | N48: =IF(L48>=2000,30,IF(L48>=1000,20,IF(L48>=500,10,5))) | O48: 20 | P48: =M48+N48+O48 | Q48: A11843123
A49: =HYPERLINK("https://www.google.com/search?q=A11970594+Miami+MLS+listing", "A11970594") | B49: 2433 NW 97th St | C49: 33147 | D49: Miami-Dade County | E49: Duplex | F49: 2 | G49: 724900 | H49: 5800 | I49: =H49/G49 | J49: =H49*(1-Assumptions!$B$4) | K49: =PMT(Assumptions!$B$2/12, 360, -G49*(1-Assumptions!$B$3)) | L49: =J49+K49 | M49: =IF(I49>=0.01,50,IF(I49>=0.0095,37,IF(I49>=0.009,25,12))) | N49: =IF(L49>=2000,30,IF(L49>=1000,20,IF(L49>=500,10,5))) | O49: 20 | P49: =M49+N49+O49 | Q49: A11970594
A50: =HYPERLINK("https://www.google.com/search?q=A11974830+Miami+MLS+listing", "A11974830") | B50: 101 NW 68th Ter | C50: 33150 | D50: Miami-Dade County | E50: Duplex | F50: 2 | G50: 1050000 | H50: 6400 | I50: =H50/G50 | J50: =H50*(1-Assumptions!$B$4) | K50: =PMT(Assumptions!$B$2/12, 360, -G50*(1-Assumptions!$B$3)) | L50: =J50+K50 | M50: =IF(I50>=0.01,50,IF(I50>=0.0095,37,IF(I50>=0.009,25,12))) | N50: =IF(L50>=2000,30,IF(L50>=1000,20,IF(L50>=500,10,5))) | O50: 20 | P50: =M50+N50+O50 | Q50: A11974830
A51: =HYPERLINK("https://www.google.com/search?q=A11962134+Miami+MLS+listing", "A11962134") | B51: 2840-2842 NW 13th St | C51: 33125 | D51: Miami-Dade County | E51: Duplex | F51: 2 | G51: 1095000 | H51: 6300 | I51: =H51/G51 | J51: =H51*(1-Assumptions!$B$4) | K51: =PMT(Assumptions!$B$2/12, 360, -G51*(1-Assumptions!$B$3)) | L51: =J51+K51 | M51: =IF(I51>=0.01,50,IF(I51>=0.0095,37,IF(I51>=0.009,25,12))) | N51: =IF(L51>=2000,30,IF(L51>=1000,20,IF(L51>=500,10,5))) | O51: 20 | P51: =M51+N51+O51 | Q51: A11962134
A52: =HYPERLINK("https://www.google.com/search?q=A11940973+Miami+MLS+listing", "A11940973") | B52: 1230 NW 35th St | C52: 33142 | D52: Miami-Dade County | E52: Triplex | F52: 3 | G52: 710000 | H52: 6250 | I52: =H52/G52 | J52: =H52*(1-Assumptions!$B$4) | K52: =PMT(Assumptions!$B$2/12, 360, -G52*(1-Assumptions!$B$3)) | L52: =J52+K52 | M52: =IF(I52>=0.01,50,IF(I52>=0.0095,37,IF(I52>=0.009,25,12))) | N52: =IF(L52>=2000,30,IF(L52>=1000,20,IF(L52>=500,10,5))) | O52: 20 | P52: =M52+N52+O52 | Q52: A11940973
A53: =HYPERLINK("https://www.google.com/search?q=A11942087+Miami+MLS+listing", "A11942087") | B53: 16585 NE 3 AVE | C53: 33162 | D53: Miami-Dade County | E53: Fourplex | F53: 4 | G53: 2950000 | H53: 6200 | I53: =H53/G53 | J53: =H53*(1-Assumptions!$B$4) | K53: =PMT(Assumptions!$B$2/12, 360, -G53*(1-Assumptions!$B$3)) | L53: =J53+K53 | M53: =IF(I53>=0.01,50,IF(I53>=0.0095,37,IF(I53>=0.009,25,12))) | N53: =IF(L53>=2000,30,IF(L53>=1000,20,IF(L53>=500,10,5))) | O53: 20 | P53: =M53+N53+O53 | Q53: A11942087
A54: =HYPERLINK("https://www.google.com/search?q=A11674866+Miami+MLS+listing", "A11674866") | B54: 242 NE 55th Ter | C54: 33137 | D54: Miami-Dade County | E54: Duplex | F54: 2 | G54: 1240000 | H54: 6400 | I54: =H54/G54 | J54: =H54*(1-Assumptions!$B$4) | K54: =PMT(Assumptions!$B$2/12, 360, -G54*(1-Assumptions!$B$3)) | L54: =J54+K54 | M54: =IF(I54>=0.01,50,IF(I54>=0.0095,37,IF(I54>=0.009,25,12))) | N54: =IF(L54>=2000,30,IF(L54>=1000,20,IF(L54>=500,10,5))) | O54: 20 | P54: =M54+N54+O54 | Q54: A11674866
A55: =HYPERLINK("https://www.google.com/search?q=A11946382+Miami+MLS+listing", "A11946382") | B55: 2275 SW 61st Ave | C55: 33155 | D55: Miami-Dade County | E55: Duplex | F55: 2 | G55: 1150000 | H55: 6200 | I55: =H55/G55 | J55: =H55*(1-Assumptions!$B$4) | K55: =PMT(Assumptions!$B$2/12, 360, -G55*(1-Assumptions!$B$3)) | L55: =J55+K55 | M55: =IF(I55>=0.01,50,IF(I55>=0.0095,37,IF(I55>=0.009,25,12))) | N55: =IF(L55>=2000,30,IF(L55>=1000,20,IF(L55>=500,10,5))) | O55: 20 | P55: =M55+N55+O55 | Q55: A11946382
A56: =HYPERLINK("https://www.google.com/search?q=A11928955+Miami+MLS+listing", "A11928955") | B56: 1910 NW 72nd St | C56: 33147 | D56: Miami-Dade County | E56: Fourplex | F56: 4 | G56: 1125000 | H56: 6139 | I56: =H56/G56 | J56: =H56*(1-Assumptions!$B$4) | K56: =PMT(Assumptions!$B$2/12, 360, -G56*(1-Assumptions!$B$3)) | L56: =J56+K56 | M56: =IF(I56>=0.01,50,IF(I56>=0.0095,37,IF(I56>=0.009,25,12))) | N56: =IF(L56>=2000,30,IF(L56>=1000,20,IF(L56>=500,10,5))) | O56: 20 | P56: =M56+N56+O56 | Q56: A11928955
A57: =HYPERLINK("https://www.google.com/search?q=A11912831+Miami+MLS+listing", "A11912831") | B57: 163 NW 68th Ter | C57: 33150 | D57: Miami-Dade County | E57: Duplex | F57: 2 | G57: 800000 | H57: 6100 | I57: =H57/G57 | J57: =H57*(1-Assumptions!$B$4) | K57: =PMT(Assumptions!$B$2/12, 360, -G57*(1-Assumptions!$B$3)) | L57: =J57+K57 | M57: =IF(I57>=0.01,50,IF(I57>=0.0095,37,IF(I57>=0.009,25,12))) | N57: =IF(L57>=2000,30,IF(L57>=1000,20,IF(L57>=500,10,5))) | O57: 20 | P57: =M57+N57+O57 | Q57: A11912831
A58: =HYPERLINK("https://www.google.com/search?q=A11841532+Miami+MLS+listing", "A11841532") | B58: 2121-2125 NW 72nd st | C58: 33147 | D58: Miami-Dade County | E58: Duplex | F58: 2 | G58: 719000 | H58: 6000 | I58: =H58/G58 | J58: =H58*(1-Assumptions!$B$4) | K58: =PMT(Assumptions!$B$2/12, 360, -G58*(1-Assumptions!$B$3)) | L58: =J58+K58 | M58: =IF(I58>=0.01,50,IF(I58>=0.0095,37,IF(I58>=0.009,25,12))) | N58: =IF(L58>=2000,30,IF(L58>=1000,20,IF(L58>=500,10,5))) | O58: 20 | P58: =M58+N58+O58 | Q58: A11841532
A59: =HYPERLINK("https://www.google.com/search?q=A11954020+Miami+MLS+listing", "A11954020") | B59: 11515 NE 12th Ave | C59: 33161 | D59: Miami-Dade County | E59: Duplex | F59: 2 | G59: 880000 | H59: 5900 | I59: =H59/G59 | J59: =H59*(1-Assumptions!$B$4) | K59: =PMT(Assumptions!$B$2/12, 360, -G59*(1-Assumptions!$B$3)) | L59: =J59+K59 | M59: =IF(I59>=0.01,50,IF(I59>=0.0095,37,IF(I59>=0.009,25,12))) | N59: =IF(L59>=2000,30,IF(L59>=1000,20,IF(L59>=500,10,5))) | O59: 20 | P59: =M59+N59+O59 | Q59: A11954020
A60: =HYPERLINK("https://www.google.com/search?q=A11883153+Miami+MLS+listing", "A11883153") | B60: 1410 SW 22nd Ave | C60: 33145 | D60: Miami-Dade County | E60: Duplex | F60: 2 | G60: 750000 | H60: 5900 | I60: =H60/G60 | J60: =H60*(1-Assumptions!$B$4) | K60: =PMT(Assumptions!$B$2/12, 360, -G60*(1-Assumptions!$B$3)) | L60: =J60+K60 | M60: =IF(I60>=0.01,50,IF(I60>=0.0095,37,IF(I60>=0.009,25,12))) | N60: =IF(L60>=2000,30,IF(L60>=1000,20,IF(L60>=500,10,5))) | O60: 20 | P60: =M60+N60+O60 | Q60: A11883153
A61: =HYPERLINK("https://www.google.com/search?q=A11953583+Miami+MLS+listing", "A11953583") | B61: 2722 SW 5th St | C61: 33135 | D61: Miami-Dade County | E61: Duplex | F61: 2 | G61: 935000 | H61: 5900 | I61: =H61/G61 | J61: =H61*(1-Assumptions!$B$4) | K61: =PMT(Assumptions!$B$2/12, 360, -G61*(1-Assumptions!$B$3)) | L61: =J61+K61 | M61: =IF(I61>=0.01,50,IF(I61>=0.0095,37,IF(I61>=0.009,25,12))) | N61: =IF(L61>=2000,30,IF(L61>=1000,20,IF(L61>=500,10,5))) | O61: 20 | P61: =M61+N61+O61 | Q61: A11953583
A62: =HYPERLINK("https://www.google.com/search?q=A11763668+Miami+MLS+listing", "A11763668") | B62: 929 SW 12th Ave | C62: 33130 | D62: Miami-Dade County | E62: Duplex | F62: 2 | G62: 899000 | H62: 5850 | I62: =H62/G62 | J62: =H62*(1-Assumptions!$B$4) | K62: =PMT(Assumptions!$B$2/12, 360, -G62*(1-Assumptions!$B$3)) | L62: =J62+K62 | M62: =IF(I62>=0.01,50,IF(I62>=0.0095,37,IF(I62>=0.009,25,12))) | N62: =IF(L62>=2000,30,IF(L62>=1000,20,IF(L62>=500,10,5))) | O62: 20 | P62: =M62+N62+O62 | Q62: A11763668
A63: =HYPERLINK("https://www.google.com/search?q=A11972374+Miami+MLS+listing", "A11972374") | B63: 11020 NE 10th Ave | C63: 33161 | D63: Miami-Dade County | E63: Duplex | F63: 2 | G63: 860000 | H63: 5600 | I63: =H63/G63 | J63: =H63*(1-Assumptions!$B$4) | K63: =PMT(Assumptions!$B$2/12, 360, -G63*(1-Assumptions!$B$3)) | L63: =J63+K63 | M63: =IF(I63>=0.01,50,IF(I63>=0.0095,37,IF(I63>=0.009,25,12))) | N63: =IF(L63>=2000,30,IF(L63>=1000,20,IF(L63>=500,10,5))) | O63: 20 | P63: =M63+N63+O63 | Q63: A11972374
A64: =HYPERLINK("https://www.google.com/search?q=A11704349+Miami+MLS+listing", "A11704349") | B64: 1838 NW 18th St | C64: 33125 | D64: Miami-Dade County | E64: Duplex | F64: 2 | G64: 715000 | H64: 5300 | I64: =H64/G64 | J64: =H64*(1-Assumptions!$B$4) | K64: =PMT(Assumptions!$B$2/12, 360, -G64*(1-Assumptions!$B$3)) | L64: =J64+K64 | M64: =IF(I64>=0.01,50,IF(I64>=0.0095,37,IF(I64>=0.009,25,12))) | N64: =IF(L64>=2000,30,IF(L64>=1000,20,IF(L64>=500,10,5))) | O64: 20 | P64: =M64+N64+O64 | Q64: A11704349
A65: =HYPERLINK("https://www.google.com/search?q=A11933410+Miami+MLS+listing", "A11933410") | B65: 9210 NW 4th Ave | C65: 33150 | D65: Miami-Dade County | E65: Duplex | F65: 2 | G65: 749000 | H65: 5600 | I65: =H65/G65 | J65: =H65*(1-Assumptions!$B$4) | K65: =PMT(Assumptions!$B$2/12, 360, -G65*(1-Assumptions!$B$3)) | L65: =J65+K65 | M65: =IF(I65>=0.01,50,IF(I65>=0.0095,37,IF(I65>=0.009,25,12))) | N65: =IF(L65>=2000,30,IF(L65>=1000,20,IF(L65>=500,10,5))) | O65: 20 | P65: =M65+N65+O65 | Q65: A11933410
A66: =HYPERLINK("https://www.google.com/search?q=A11851454+Miami+MLS+listing", "A11851454") | B66: 3066 NW 92nd St | C66: 33147 | D66: Miami-Dade County | E66: Duplex | F66: 2 | G66: 850000 | H66: 5600 | I66: =H66/G66 | J66: =H66*(1-Assumptions!$B$4) | K66: =PMT(Assumptions!$B$2/12, 360, -G66*(1-Assumptions!$B$3)) | L66: =J66+K66 | M66: =IF(I66>=0.01,50,IF(I66>=0.0095,37,IF(I66>=0.009,25,12))) | N66: =IF(L66>=2000,30,IF(L66>=1000,20,IF(L66>=500,10,5))) | O66: 20 | P66: =M66+N66+O66 | Q66: A11851454
A67: =HYPERLINK("https://www.google.com/search?q=A11873091+Miami+MLS+listing", "A11873091") | B67: 180 NW 59th St | C67: 33127 | D67: Miami-Dade County | E67: Fourplex | F67: 4 | G67: 1300000 | H67: 5550 | I67: =H67/G67 | J67: =H67*(1-Assumptions!$B$4) | K67: =PMT(Assumptions!$B$2/12, 360, -G67*(1-Assumptions!$B$3)) | L67: =J67+K67 | M67: =IF(I67>=0.01,50,IF(I67>=0.0095,37,IF(I67>=0.009,25,12))) | N67: =IF(L67>=2000,30,IF(L67>=1000,20,IF(L67>=500,10,5))) | O67: 20 | P67: =M67+N67+O67 | Q67: A11873091
A68: =HYPERLINK("https://www.google.com/search?q=A11977960+Miami+MLS+listing", "A11977960") | B68: 12125 NE 7th Ave | C68: 33161 | D68: Miami-Dade County | E68: Duplex | F68: 2 | G68: 865000 | H68: 5500 | I68: =H68/G68 | J68: =H68*(1-Assumptions!$B$4) | K68: =PMT(Assumptions!$B$2/12, 360, -G68*(1-Assumptions!$B$3)) | L68: =J68+K68 | M68: =IF(I68>=0.01,50,IF(I68>=0.0095,37,IF(I68>=0.009,25,12))) | N68: =IF(L68>=2000,30,IF(L68>=1000,20,IF(L68>=500,10,5))) | O68: 20 | P68: =M68+N68+O68 | Q68: A11977960
A69: =HYPERLINK("https://www.google.com/search?q=A11617144+Miami+MLS+listing", "A11617144") | B69: 2752 SW 3rd St | C69: 33135 | D69: Miami-Dade County | E69: Duplex | F69: 2 | G69: 1094000 | H69: 5400 | I69: =H69/G69 | J69: =H69*(1-Assumptions!$B$4) | K69: =PMT(Assumptions!$B$2/12, 360, -G69*(1-Assumptions!$B$3)) | L69: =J69+K69 | M69: =IF(I69>=0.01,50,IF(I69>=0.0095,37,IF(I69>=0.009,25,12))) | N69: =IF(L69>=2000,30,IF(L69>=1000,20,IF(L69>=500,10,5))) | O69: 20 | P69: =M69+N69+O69 | Q69: A11617144
A70: =HYPERLINK("https://www.google.com/search?q=A11937947+Miami+MLS+listing", "A11937947") | B70: 310-312 SW 36th Ave | C70: 33135 | D70: Miami-Dade County | E70: Duplex | F70: 2 | G70: 960000 | H70: 5400 | I70: =H70/G70 | J70: =H70*(1-Assumptions!$B$4) | K70: =PMT(Assumptions!$B$2/12, 360, -G70*(1-Assumptions!$B$3)) | L70: =J70+K70 | M70: =IF(I70>=0.01,50,IF(I70>=0.0095,37,IF(I70>=0.009,25,12))) | N70: =IF(L70>=2000,30,IF(L70>=1000,20,IF(L70>=500,10,5))) | O70: 20 | P70: =M70+N70+O70 | Q70: A11937947
A71: =HYPERLINK("https://www.google.com/search?q=A11943316+Miami+MLS+listing", "A11943316") | B71: 16915 NE 4th Ave | C71: 33162 | D71: Miami-Dade County | E71: Duplex | F71: 2 | G71: 759000 | H71: 5400 | I71: =H71/G71 | J71: =H71*(1-Assumptions!$B$4) | K71: =PMT(Assumptions!$B$2/12, 360, -G71*(1-Assumptions!$B$3)) | L71: =J71+K71 | M71: =IF(I71>=0.01,50,IF(I71>=0.0095,37,IF(I71>=0.009,25,12))) | N71: =IF(L71>=2000,30,IF(L71>=1000,20,IF(L71>=500,10,5))) | O71: 20 | P71: =M71+N71+O71 | Q71: A11943316
A72: =HYPERLINK("https://www.google.com/search?q=A11940950+Miami+MLS+listing", "A11940950") | B72: 5800 NE 3rd Ave | C72: 33137 | D72: Miami-Dade County | E72: Duplex | F72: 2 | G72: 799000 | H72: 4600 | I72: =H72/G72 | J72: =H72*(1-Assumptions!$B$4) | K72: =PMT(Assumptions!$B$2/12, 360, -G72*(1-Assumptions!$B$3)) | L72: =J72+K72 | M72: =IF(I72>=0.01,50,IF(I72>=0.0095,37,IF(I72>=0.009,25,12))) | N72: =IF(L72>=2000,30,IF(L72>=1000,20,IF(L72>=500,10,5))) | O72: 20 | P72: =M72+N72+O72 | Q72: A11940950
A73: =HYPERLINK("https://www.google.com/search?q=A11897754+Miami+MLS+listing", "A11897754") | B73: 7534/7536 NW 4th Ave | C73: 33150 | D73: Miami-Dade County | E73: Duplex | F73: 2 | G73: 645000 | H73: 5400 | I73: =H73/G73 | J73: =H73*(1-Assumptions!$B$4) | K73: =PMT(Assumptions!$B$2/12, 360, -G73*(1-Assumptions!$B$3)) | L73: =J73+K73 | M73: =IF(I73>=0.01,50,IF(I73>=0.0095,37,IF(I73>=0.009,25,12))) | N73: =IF(L73>=2000,30,IF(L73>=1000,20,IF(L73>=500,10,5))) | O73: 20 | P73: =M73+N73+O73 | Q73: A11897754
A74: =HYPERLINK("https://www.google.com/search?q=A11822047+Miami+MLS+listing", "A11822047") | B74: 1924 NW 35th St | C74: 33142 | D74: Miami-Dade County | E74: Duplex | F74: 2 | G74: 950000 | H74: 6400 | I74: =H74/G74 | J74: =H74*(1-Assumptions!$B$4) | K74: =PMT(Assumptions!$B$2/12, 360, -G74*(1-Assumptions!$B$3)) | L74: =J74+K74 | M74: =IF(I74>=0.01,50,IF(I74>=0.0095,37,IF(I74>=0.009,25,12))) | N74: =IF(L74>=2000,30,IF(L74>=1000,20,IF(L74>=500,10,5))) | O74: 20 | P74: =M74+N74+O74 | Q74: A11822047
A75: =HYPERLINK("https://www.google.com/search?q=A11955083+Miami+MLS+listing", "A11955083") | B75: 2729 NW 47th St | C75: 33142 | D75: Miami-Dade County | E75: Duplex | F75: 2 | G75: 802998 | H75: 5350 | I75: =H75/G75 | J75: =H75*(1-Assumptions!$B$4) | K75: =PMT(Assumptions!$B$2/12, 360, -G75*(1-Assumptions!$B$3)) | L75: =J75+K75 | M75: =IF(I75>=0.01,50,IF(I75>=0.0095,37,IF(I75>=0.009,25,12))) | N75: =IF(L75>=2000,30,IF(L75>=1000,20,IF(L75>=500,10,5))) | O75: 20 | P75: =M75+N75+O75 | Q75: A11955083
A76: =HYPERLINK("https://www.google.com/search?q=A11975535+Miami+MLS+listing", "A11975535") | B76: 1000 7th Street | C76: 33139 | D76: Miami-Dade County | E76: Fourplex | F76: 4 | G76: 4500000 | H76: 5340 | I76: =H76/G76 | J76: =H76*(1-Assumptions!$B$4) | K76: =PMT(Assumptions!$B$2/12, 360, -G76*(1-Assumptions!$B$3)) | L76: =J76+K76 | M76: =IF(I76>=0.01,50,IF(I76>=0.0095,37,IF(I76>=0.009,25,12))) | N76: =IF(L76>=2000,30,IF(L76>=1000,20,IF(L76>=500,10,5))) | O76: 20 | P76: =M76+N76+O76 | Q76: A11975535
A77: =HYPERLINK("https://www.google.com/search?q=A11805845+Miami+MLS+listing", "A11805845") | B77: 4400 NW 1st Ave | C77: 33127 | D77: Miami-Dade County | E77: Duplex | F77: 2 | G77: 1195000 | H77: 5300 | I77: =H77/G77 | J77: =H77*(1-Assumptions!$B$4) | K77: =PMT(Assumptions!$B$2/12, 360, -G77*(1-Assumptions!$B$3)) | L77: =J77+K77 | M77: =IF(I77>=0.01,50,IF(I77>=0.0095,37,IF(I77>=0.009,25,12))) | N77: =IF(L77>=2000,30,IF(L77>=1000,20,IF(L77>=500,10,5))) | O77: 20 | P77: =M77+N77+O77 | Q77: A11805845
A78: =HYPERLINK("https://www.google.com/search?q=A11939713+Miami+MLS+listing", "A11939713") | B78: 2939 SW 21st ST | C78: 33145 | D78: Miami-Dade County | E78: Duplex | F78: 2 | G78: 6120000 | H78: 40000 | I78: =H78/G78 | J78: =H78*(1-Assumptions!$B$4) | K78: =PMT(Assumptions!$B$2/12, 360, -G78*(1-Assumptions!$B$3)) | L78: =J78+K78 | M78: =IF(I78>=0.01,50,IF(I78>=0.0095,37,IF(I78>=0.009,25,12))) | N78: =IF(L78>=2000,30,IF(L78>=1000,20,IF(L78>=500,10,5))) | O78: 20 | P78: =M78+N78+O78 | Q78: A11939713
A79: =HYPERLINK("https://www.google.com/search?q=A11929998+Miami+MLS+listing", "A11929998") | B79: 1570 NE 130th St | C79: 33161 | D79: Miami-Dade County | E79: Fourplex | F79: 4 | G79: 944000 | H79: 4575 | I79: =H79/G79 | J79: =H79*(1-Assumptions!$B$4) | K79: =PMT(Assumptions!$B$2/12, 360, -G79*(1-Assumptions!$B$3)) | L79: =J79+K79 | M79: =IF(I79>=0.01,50,IF(I79>=0.0095,37,IF(I79>=0.009,25,12))) | N79: =IF(L79>=2000,30,IF(L79>=1000,20,IF(L79>=500,10,5))) | O79: 20 | P79: =M79+N79+O79 | Q79: A11929998
A80: =HYPERLINK("https://www.google.com/search?q=A11849198+Miami+MLS+listing", "A11849198") | B80: 1574 NW 58th St | C80: 33142 | D80: Miami-Dade County | E80: Duplex | F80: 2 | G80: 590000 | H80: 4550 | I80: =H80/G80 | J80: =H80*(1-Assumptions!$B$4) | K80: =PMT(Assumptions!$B$2/12, 360, -G80*(1-Assumptions!$B$3)) | L80: =J80+K80 | M80: =IF(I80>=0.01,50,IF(I80>=0.0095,37,IF(I80>=0.009,25,12))) | N80: =IF(L80>=2000,30,IF(L80>=1000,20,IF(L80>=500,10,5))) | O80: 20 | P80: =M80+N80+O80 | Q80: A11849198
A81: =HYPERLINK("https://www.google.com/search?q=A11932161+Miami+MLS+listing", "A11932161") | B81: 1533 NW 53rd St | C81: 33142 | D81: Miami-Dade County | E81: Duplex | F81: 2 | G81: 575000 | H81: 4500 | I81: =H81/G81 | J81: =H81*(1-Assumptions!$B$4) | K81: =PMT(Assumptions!$B$2/12, 360, -G81*(1-Assumptions!$B$3)) | L81: =J81+K81 | M81: =IF(I81>=0.01,50,IF(I81>=0.0095,37,IF(I81>=0.009,25,12))) | N81: =IF(L81>=2000,30,IF(L81>=1000,20,IF(L81>=500,10,5))) | O81: 20 | P81: =M81+N81+O81 | Q81: A11932161
A82: =HYPERLINK("https://www.google.com/search?q=A11910562+Miami+MLS+listing", "A11910562") | B82: 282 NW 41st Ave | C82: 33126 | D82: Miami-Dade County | E82: Duplex | F82: 2 | G82: 750000 | H82: 2300 | I82: =H82/G82 | J82: =H82*(1-Assumptions!$B$4) | K82: =PMT(Assumptions!$B$2/12, 360, -G82*(1-Assumptions!$B$3)) | L82: =J82+K82 | M82: =IF(I82>=0.01,50,IF(I82>=0.0095,37,IF(I82>=0.009,25,12))) | N82: =IF(L82>=2000,30,IF(L82>=1000,20,IF(L82>=500,10,5))) | O82: 20 | P82: =M82+N82+O82 | Q82: A11910562
A83: =HYPERLINK("https://www.google.com/search?q=A11799039+Miami+MLS+listing", "A11799039") | B83: 16204 NE 18th Ct | C83: 33162 | D83: Miami-Dade County | E83: Duplex | F83: 2 | G83: 633000 | H83: 2400 | I83: =H83/G83 | J83: =H83*(1-Assumptions!$B$4) | K83: =PMT(Assumptions!$B$2/12, 360, -G83*(1-Assumptions!$B$3)) | L83: =J83+K83 | M83: =IF(I83>=0.01,50,IF(I83>=0.0095,37,IF(I83>=0.009,25,12))) | N83: =IF(L83>=2000,30,IF(L83>=1000,20,IF(L83>=500,10,5))) | O83: 20 | P83: =M83+N83+O83 | Q83: A11799039
A84: =HYPERLINK("https://www.google.com/search?q=A11961535+Miami+MLS+listing", "A11961535") | B84: 551 NE 67th St | C84: 33138 | D84: Miami-Dade County | E84: Duplex | F84: 2 | G84: 1250000 | H84: 2600 | I84: =H84/G84 | J84: =H84*(1-Assumptions!$B$4) | K84: =PMT(Assumptions!$B$2/12, 360, -G84*(1-Assumptions!$B$3)) | L84: =J84+K84 | M84: =IF(I84>=0.01,50,IF(I84>=0.0095,37,IF(I84>=0.009,25,12))) | N84: =IF(L84>=2000,30,IF(L84>=1000,20,IF(L84>=500,10,5))) | O84: 20 | P84: =M84+N84+O84 | Q84: A11961535
A85: =HYPERLINK("https://www.google.com/search?q=A11904937+Miami+MLS+listing", "A11904937") | B85: 3376 NW 49th St | C85: 33142 | D85: Miami-Dade County | E85: Duplex | F85: 2 | G85: 700000 | H85: 2600 | I85: =H85/G85 | J85: =H85*(1-Assumptions!$B$4) | K85: =PMT(Assumptions!$B$2/12, 360, -G85*(1-Assumptions!$B$3)) | L85: =J85+K85 | M85: =IF(I85>=0.01,50,IF(I85>=0.0095,37,IF(I85>=0.009,25,12))) | N85: =IF(L85>=2000,30,IF(L85>=1000,20,IF(L85>=500,10,5))) | O85: 20 | P85: =M85+N85+O85 | Q85: A11904937
A86: =HYPERLINK("https://www.google.com/search?q=A11972053+Miami+MLS+listing", "A11972053") | B86: 1064 NW 103rd St | C86: 33150 | D86: Miami-Dade County | E86: Duplex | F86: 2 | G86: 585000 | H86: 2600 | I86: =H86/G86 | J86: =H86*(1-Assumptions!$B$4) | K86: =PMT(Assumptions!$B$2/12, 360, -G86*(1-Assumptions!$B$3)) | L86: =J86+K86 | M86: =IF(I86>=0.01,50,IF(I86>=0.0095,37,IF(I86>=0.009,25,12))) | N86: =IF(L86>=2000,30,IF(L86>=1000,20,IF(L86>=500,10,5))) | O86: 20 | P86: =M86+N86+O86 | Q86: A11972053
A87: =HYPERLINK("https://www.google.com/search?q=A11915643+Miami+MLS+listing", "A11915643") | B87: 2009 NW 34th St | C87: 33142 | D87: Miami-Dade County | E87: Duplex | F87: 2 | G87: 675000 | H87: 2700 | I87: =H87/G87 | J87: =H87*(1-Assumptions!$B$4) | K87: =PMT(Assumptions!$B$2/12, 360, -G87*(1-Assumptions!$B$3)) | L87: =J87+K87 | M87: =IF(I87>=0.01,50,IF(I87>=0.0095,37,IF(I87>=0.009,25,12))) | N87: =IF(L87>=2000,30,IF(L87>=1000,20,IF(L87>=500,10,5))) | O87: 20 | P87: =M87+N87+O87 | Q87: A11915643
A88: =HYPERLINK("https://www.google.com/search?q=A11862936+Miami+MLS+listing", "A11862936") | B88: 13201 Memorial Hwy | C88: 33161 | D88: Miami-Dade County | E88: Duplex | F88: 2 | G88: 4680000 | H88: 2800 | I88: =H88/G88 | J88: =H88*(1-Assumptions!$B$4) | K88: =PMT(Assumptions!$B$2/12, 360, -G88*(1-Assumptions!$B$3)) | L88: =J88+K88 | M88: =IF(I88>=0.01,50,IF(I88>=0.0095,37,IF(I88>=0.009,25,12))) | N88: =IF(L88>=2000,30,IF(L88>=1000,20,IF(L88>=500,10,5))) | O88: 20 | P88: =M88+N88+O88 | Q88: A11862936
A89: =HYPERLINK("https://www.google.com/search?q=A11944032+Miami+MLS+listing", "A11944032") | B89: 1900 NW 88th St | C89: 33147 | D89: Miami-Dade County | E89: Duplex | F89: 2 | G89: 520000 | H89: 2925 | I89: =H89/G89 | J89: =H89*(1-Assumptions!$B$4) | K89: =PMT(Assumptions!$B$2/12, 360, -G89*(1-Assumptions!$B$3)) | L89: =J89+K89 | M89: =IF(I89>=0.01,50,IF(I89>=0.0095,37,IF(I89>=0.009,25,12))) | N89: =IF(L89>=2000,30,IF(L89>=1000,20,IF(L89>=500,10,5))) | O89: 20 | P89: =M89+N89+O89 | Q89: A11944032
A90: =HYPERLINK("https://www.google.com/search?q=A11938592+Miami+MLS+listing", "A11938592") | B90: 3601 SW 7th St | C90: 33135 | D90: Miami-Dade County | E90: Duplex | F90: 2 | G90: 850000 | H90: 2950 | I90: =H90/G90 | J90: =H90*(1-Assumptions!$B$4) | K90: =PMT(Assumptions!$B$2/12, 360, -G90*(1-Assumptions!$B$3)) | L90: =J90+K90 | M90: =IF(I90>=0.01,50,IF(I90>=0.0095,37,IF(I90>=0.009,25,12))) | N90: =IF(L90>=2000,30,IF(L90>=1000,20,IF(L90>=500,10,5))) | O90: 20 | P90: =M90+N90+O90 | Q90: A11938592
A91: =HYPERLINK("https://www.google.com/search?q=A11919512+Miami+MLS+listing", "A11919512") | B91: 9700 NW 20th Ave | C91: 33147 | D91: Miami-Dade County | E91: Fourplex | F91: 4 | G91: 749000 | H91: 3150 | I91: =H91/G91 | J91: =H91*(1-Assumptions!$B$4) | K91: =PMT(Assumptions!$B$2/12, 360, -G91*(1-Assumptions!$B$3)) | L91: =J91+K91 | M91: =IF(I91>=0.01,50,IF(I91>=0.0095,37,IF(I91>=0.009,25,12))) | N91: =IF(L91>=2000,30,IF(L91>=1000,20,IF(L91>=500,10,5))) | O91: 20 | P91: =M91+N91+O91 | Q91: A11919512
A92: =HYPERLINK("https://www.google.com/search?q=A11872704+Miami+MLS+listing", "A11872704") | B92: 1325 SW 6th St | C92: 33135 | D92: Miami-Dade County | E92: Fourplex | F92: 4 | G92: 700000 | H92: 3200 | I92: =H92/G92 | J92: =H92*(1-Assumptions!$B$4) | K92: =PMT(Assumptions!$B$2/12, 360, -G92*(1-Assumptions!$B$3)) | L92: =J92+K92 | M92: =IF(I92>=0.01,50,IF(I92>=0.0095,37,IF(I92>=0.009,25,12))) | N92: =IF(L92>=2000,30,IF(L92>=1000,20,IF(L92>=500,10,5))) | O92: 20 | P92: =M92+N92+O92 | Q92: A11872704
A93: =HYPERLINK("https://www.google.com/search?q=A11909683+Miami+MLS+listing", "A11909683") | B93: 53 NW 68th Ter | C93: 33150 | D93: Miami-Dade County | E93: Duplex | F93: 2 | G93: 800000 | H93: 3200 | I93: =H93/G93 | J93: =H93*(1-Assumptions!$B$4) | K93: =PMT(Assumptions!$B$2/12, 360, -G93*(1-Assumptions!$B$3)) | L93: =J93+K93 | M93: =IF(I93>=0.01,50,IF(I93>=0.0095,37,IF(I93>=0.009,25,12))) | N93: =IF(L93>=2000,30,IF(L93>=1000,20,IF(L93>=500,10,5))) | O93: 20 | P93: =M93+N93+O93 | Q93: A11909683
A94: =HYPERLINK("https://www.google.com/search?q=A11893705+Miami+MLS+listing", "A11893705") | B94: 300 NW 13th Ave | C94: 33125 | D94: Miami-Dade County | E94: Duplex | F94: 2 | G94: 950000 | H94: 3275 | I94: =H94/G94 | J94: =H94*(1-Assumptions!$B$4) | K94: =PMT(Assumptions!$B$2/12, 360, -G94*(1-Assumptions!$B$3)) | L94: =J94+K94 | M94: =IF(I94>=0.01,50,IF(I94>=0.0095,37,IF(I94>=0.009,25,12))) | N94: =IF(L94>=2000,30,IF(L94>=1000,20,IF(L94>=500,10,5))) | O94: 20 | P94: =M94+N94+O94 | Q94: A11893705
A95: =HYPERLINK("https://www.google.com/search?q=A11951982+Miami+MLS+listing", "A11951982") | B95: 1786 NW 53rd St | C95: 33142 | D95: Miami-Dade County | E95: Duplex | F95: 2 | G95: 500000 | H95: 3290 | I95: =H95/G95 | J95: =H95*(1-Assumptions!$B$4) | K95: =PMT(Assumptions!$B$2/12, 360, -G95*(1-Assumptions!$B$3)) | L95: =J95+K95 | M95: =IF(I95>=0.01,50,IF(I95>=0.0095,37,IF(I95>=0.009,25,12))) | N95: =IF(L95>=2000,30,IF(L95>=1000,20,IF(L95>=500,10,5))) | O95: 20 | P95: =M95+N95+O95 | Q95: A11951982
A96: =HYPERLINK("https://www.google.com/search?q=A11787541+Miami+MLS+listing", "A11787541") | B96: 7803 NW Miami Pl | C96: 33150 | D96: Miami-Dade County | E96: Triplex | F96: 3 | G96: 550000 | H96: 3300 | I96: =H96/G96 | J96: =H96*(1-Assumptions!$B$4) | K96: =PMT(Assumptions!$B$2/12, 360, -G96*(1-Assumptions!$B$3)) | L96: =J96+K96 | M96: =IF(I96>=0.01,50,IF(I96>=0.0095,37,IF(I96>=0.009,25,12))) | N96: =IF(L96>=2000,30,IF(L96>=1000,20,IF(L96>=500,10,5))) | O96: 20 | P96: =M96+N96+O96 | Q96: A11787541
A97: =HYPERLINK("https://www.google.com/search?q=A11944493+Miami+MLS+listing", "A11944493") | B97: 36 NE 64th Ter | C97: 33138 | D97: Miami-Dade County | E97: Duplex | F97: 2 | G97: 739000 | H97: 2300 | I97: =H97/G97 | J97: =H97*(1-Assumptions!$B$4) | K97: =PMT(Assumptions!$B$2/12, 360, -G97*(1-Assumptions!$B$3)) | L97: =J97+K97 | M97: =IF(I97>=0.01,50,IF(I97>=0.0095,37,IF(I97>=0.009,25,12))) | N97: =IF(L97>=2000,30,IF(L97>=1000,20,IF(L97>=500,10,5))) | O97: 20 | P97: =M97+N97+O97 | Q97: A11944493
A98: =HYPERLINK("https://www.google.com/search?q=A11771367+Miami+MLS+listing", "A11771367") | B98: 1730 SW 72nd Ct | C98: 33155 | D98: Miami-Dade County | E98: Duplex | F98: 2 | G98: 899000 | H98: 2100 | I98: =H98/G98 | J98: =H98*(1-Assumptions!$B$4) | K98: =PMT(Assumptions!$B$2/12, 360, -G98*(1-Assumptions!$B$3)) | L98: =J98+K98 | M98: =IF(I98>=0.01,50,IF(I98>=0.0095,37,IF(I98>=0.009,25,12))) | N98: =IF(L98>=2000,30,IF(L98>=1000,20,IF(L98>=500,10,5))) | O98: 20 | P98: =M98+N98+O98 | Q98: A11771367
A99: =HYPERLINK("https://www.google.com/search?q=A11812109+Miami+MLS+listing", "A11812109") | B99: 901 SW 34th Ave | C99: 33135 | D99: Miami-Dade County | E99: Triplex | F99: 3 | G99: 650000 | H99: 2000 | I99: =H99/G99 | J99: =H99*(1-Assumptions!$B$4) | K99: =PMT(Assumptions!$B$2/12, 360, -G99*(1-Assumptions!$B$3)) | L99: =J99+K99 | M99: =IF(I99>=0.01,50,IF(I99>=0.0095,37,IF(I99>=0.009,25,12))) | N99: =IF(L99>=2000,30,IF(L99>=1000,20,IF(L99>=500,10,5))) | O99: 20 | P99: =M99+N99+O99 | Q99: A11812109
A100: =HYPERLINK("https://www.google.com/search?q=A11919729+Miami+MLS+listing", "A11919729") | B100: 105 NW 58th St | C100: 33127 | D100: Miami-Dade County | E100: Triplex | F100: 3 | G100: 599000 | H100: 1600 | I100: =H100/G100 | J100: =H100*(1-Assumptions!$B$4) | K100: =PMT(Assumptions!$B$2/12, 360, -G100*(1-Assumptions!$B$3)) | L100: =J100+K100 | M100: =IF(I100>=0.01,50,IF(I100>=0.0095,37,IF(I100>=0.009,25,12))) | N100: =IF(L100>=2000,30,IF(L100>=1000,20,IF(L100>=500,10,5))) | O100: 20 | P100: =M100+N100+O100 | Q100: A11919729
...

Sheet Excluded
A1: Address | B1: MLS ID | C1: Reason Excluded
A2: 414 SW 15th Ave | B2: A11856786 | C2: Incomplete Data
A3: 676 SW 1st St | B3: A11705841 | C3: Incomplete Data
A4: 231 SW 8th Ct | B4: A11907387 | C4: Incomplete Data
A5: 1440-1444 NE 147 STREET | B5: A11900457 | C5: Incomplete Data
A6: 236 NE 1st St | B6: A11917289 | C6: Incomplete Data
A7: 791 NW 22nd Pl | B7: A11771061 | C7: Incomplete Data
A8: 190 NW 57th St | B8: A11509328 | C8: Incomplete Data
A9: 22 NE 59th St | B9: A11611294 | C9: Incomplete Data
A10: 440 SW 5th Ave | B10: A11441503 | C10: Incomplete Data
A11: 5431 & 5433 NW 5th Ave | B11: A11761237 | C11: Incomplete Data
A12: 1080 NW 65th St | B12: A11916482 | C12: Incomplete Data
... A773: 16020 SW 208th Ave | B773: A11930288 | C773: Income anomaly — wrong income data, Issue 6
